<annotation>
  <folder>VOC2007</folder>
  <filename>190119_183240_00166796.jpg</filename>
  <source>
    <database>The VOC2007 Database</database>
    <annotation>PASCAL VOC2007</annotation>
    <image>flickr</image>
    <flickrid />
  </source>
  <owner>
    <flickrid />
    <name />
  </owner>
  <size>
    <width>487</width>
    <height>577</height>
    <depth>3</depth>
  </size>
  <segmented>0</segmented>
  <object>
    <name>Knife</name>
    <pose>Left</pose>
    <truncated>0</truncated>
    <difficult>0</difficult>
    <bndbox>
      <xmin>307.0</xmin>
      <ymin>446.0</ymin>
      <xmax>396.0</xmax>
      <ymax>574.0</ymax>
    </bndbox>
  </object>
  <object>
    <name>Black nail lighter</name>
    <pose>Left</pose>
    <truncated>0</truncated>
    <difficult>0</difficult>
    <bndbox>
      <xmin>164.0</xmin>
      <ymin>469.0</ymin>
      <xmax>252.0</xmax>
      <ymax>603.0</ymax>
    </bndbox>
  </object>
</annotation>
