<annotation>
  <folder>VOC2007</folder>
  <filename>190125_182734_00174927.jpg</filename>
  <source>
    <database>The VOC2007 Database</database>
    <annotation>PASCAL VOC2007</annotation>
    <image>flickr</image>
    <flickrid />
  </source>
  <owner>
    <flickrid />
    <name />
  </owner>
  <size>
    <width>1151</width>
    <height>490</height>
    <depth>3</depth>
  </size>
  <segmented>0</segmented>
  <object>
    <name>Knife</name>
    <pose>Left</pose>
    <truncated>0</truncated>
    <difficult>0</difficult>
    <bndbox>
      <xmin>146.0</xmin>
      <ymin>171.0</ymin>
      <xmax>232.0</xmax>
      <ymax>268.0</ymax>
    </bndbox>
  </object>
  <object>
    <name>Knife</name>
    <pose>Left</pose>
    <truncated>0</truncated>
    <difficult>0</difficult>
    <bndbox>
      <xmin>587.0</xmin>
      <ymin>103.0</ymin>
      <xmax>648.0</xmax>
      <ymax>321.0</ymax>
    </bndbox>
  </object>
  <object>
    <name>Black nail lighter</name>
    <pose>Left</pose>
    <truncated>0</truncated>
    <difficult>0</difficult>
    <bndbox>
      <xmin>273.0</xmin>
      <ymin>217.0</ymin>
      <xmax>339.0</xmax>
      <ymax>299.0</ymax>
    </bndbox>
  </object>
  <object>
    <name>Black nail lighter</name>
    <pose>Left</pose>
    <truncated>0</truncated>
    <difficult>0</difficult>
    <bndbox>
      <xmin>797.0</xmin>
      <ymin>321.0</ymin>
      <xmax>827.0</xmax>
      <ymax>410.0</ymax>
    </bndbox>
  </object>
</annotation>
