<annotation>
  <folder>VOC2007</folder>
  <filename>190127_101838_00177299.jpg</filename>
  <source>
    <database>The VOC2007 Database</database>
    <annotation>PASCAL VOC2007</annotation>
    <image>flickr</image>
    <flickrid />
  </source>
  <owner>
    <flickrid />
    <name />
  </owner>
  <size>
    <width>455</width>
    <height>436</height>
    <depth>3</depth>
  </size>
  <segmented>0</segmented>
  <object>
    <name>Iron shell lighter</name>
    <pose>Left</pose>
    <truncated>0</truncated>
    <difficult>0</difficult>
    <bndbox>
      <xmin>251.0</xmin>
      <ymin>205.0</ymin>
      <xmax>334.0</xmax>
      <ymax>293.0</ymax>
    </bndbox>
  </object>
  <object>
    <name>Knife</name>
    <pose>Left</pose>
    <truncated>0</truncated>
    <difficult>0</difficult>
    <bndbox>
      <xmin>117.0</xmin>
      <ymin>361.0</ymin>
      <xmax>146.0</xmax>
      <ymax>454.0</ymax>
    </bndbox>
  </object>
  <object>
    <name>Black nail lighter</name>
    <pose>Left</pose>
    <truncated>0</truncated>
    <difficult>0</difficult>
    <bndbox>
      <xmin>99.0</xmin>
      <ymin>258.0</ymin>
      <xmax>114.0</xmax>
      <ymax>304.0</ymax>
    </bndbox>
  </object>
  <object>
    <name>Black nail lighter</name>
    <pose>Left</pose>
    <truncated>0</truncated>
    <difficult>0</difficult>
    <bndbox>
      <xmin>164.0</xmin>
      <ymin>244.0</ymin>
      <xmax>180.0</xmax>
      <ymax>290.0</ymax>
    </bndbox>
  </object>
</annotation>
