<annotation>
  <folder>VOC2007</folder>
  <filename>190127_145253_00178623.jpg</filename>
  <source>
    <database>The VOC2007 Database</database>
    <annotation>PASCAL VOC2007</annotation>
    <image>flickr</image>
    <flickrid />
  </source>
  <owner>
    <flickrid />
    <name />
  </owner>
  <size>
    <width>691</width>
    <height>462</height>
    <depth>3</depth>
  </size>
  <segmented>0</segmented>
  <object>
    <name>Power and batteries</name>
    <pose>Left</pose>
    <truncated>0</truncated>
    <difficult>0</difficult>
    <bndbox>
      <xmin>200.0</xmin>
      <ymin>189.0</ymin>
      <xmax>234.0</xmax>
      <ymax>212.0</ymax>
    </bndbox>
  </object>
  <object>
    <name>Power and batteries</name>
    <pose>Left</pose>
    <truncated>0</truncated>
    <difficult>0</difficult>
    <bndbox>
      <xmin>216.0</xmin>
      <ymin>189.0</ymin>
      <xmax>250.0</xmax>
      <ymax>214.0</ymax>
    </bndbox>
  </object>
  <object>
    <name>Power and batteries</name>
    <pose>Left</pose>
    <truncated>0</truncated>
    <difficult>0</difficult>
    <bndbox>
      <xmin>233.0</xmin>
      <ymin>191.0</ymin>
      <xmax>268.0</xmax>
      <ymax>214.0</ymax>
    </bndbox>
  </object>
  <object>
    <name>Power and batteries</name>
    <pose>Left</pose>
    <truncated>0</truncated>
    <difficult>0</difficult>
    <bndbox>
      <xmin>342.0</xmin>
      <ymin>185.0</ymin>
      <xmax>360.0</xmax>
      <ymax>216.0</ymax>
    </bndbox>
  </object>
</annotation>
