<annotation>
  <folder>VOC2007</folder>
  <filename>190127_143331_00178492.jpg</filename>
  <source>
    <database>The VOC2007 Database</database>
    <annotation>PASCAL VOC2007</annotation>
    <image>flickr</image>
    <flickrid />
  </source>
  <owner>
    <flickrid />
    <name />
  </owner>
  <size>
    <width>706</width>
    <height>328</height>
    <depth>3</depth>
  </size>
  <segmented>0</segmented>
  <object>
    <name>电源和电池</name>
    <pose>Left</pose>
    <truncated>0</truncated>
    <difficult>0</difficult>
    <bndbox>
      <xmin>207.0</xmin>
      <ymin>117.0</ymin>
      <xmax>276.0</xmax>
      <ymax>173.0</ymax>
    </bndbox>
  </object>
  <object>
    <name>黑钉打火机</name>
    <pose>Left</pose>
    <truncated>0</truncated>
    <difficult>0</difficult>
    <bndbox>
      <xmin>396.0</xmin>
      <ymin>81.0</ymin>
      <xmax>443.0</xmax>
      <ymax>186.0</ymax>
    </bndbox>
  </object>
  <object>
    <name>黑钉打火机</name>
    <pose>Left</pose>
    <truncated>0</truncated>
    <difficult>0</difficult>
    <bndbox>
      <xmin>411.0</xmin>
      <ymin>113.0</ymin>
      <xmax>456.0</xmax>
      <ymax>196.0</ymax>
    </bndbox>
  </object>
</annotation>
