<annotation>
  <folder>VOC2007</folder>
  <filename>190127_143358_00178499.jpg</filename>
  <source>
    <database>The VOC2007 Database</database>
    <annotation>PASCAL VOC2007</annotation>
    <image>flickr</image>
    <flickrid />
  </source>
  <owner>
    <flickrid />
    <name />
  </owner>
  <size>
    <width>1151</width>
    <height>480</height>
    <depth>3</depth>
  </size>
  <segmented>0</segmented>
  <object>
    <name>电源和电池</name>
    <pose>Left</pose>
    <truncated>0</truncated>
    <difficult>0</difficult>
    <bndbox>
      <xmin>215.0</xmin>
      <ymin>280.0</ymin>
      <xmax>255.0</xmax>
      <ymax>320.0</ymax>
    </bndbox>
  </object>
  <object>
    <name>电源和电池</name>
    <pose>Left</pose>
    <truncated>0</truncated>
    <difficult>0</difficult>
    <bndbox>
      <xmin>276.0</xmin>
      <ymin>343.0</ymin>
      <xmax>338.0</xmax>
      <ymax>402.0</ymax>
    </bndbox>
  </object>
  <object>
    <name>黑钉打火机</name>
    <pose>Left</pose>
    <truncated>0</truncated>
    <difficult>0</difficult>
    <bndbox>
      <xmin>684.0</xmin>
      <ymin>142.0</ymin>
      <xmax>708.0</xmax>
      <ymax>235.0</ymax>
    </bndbox>
  </object>
  <object>
    <name>黑钉打火机</name>
    <pose>Left</pose>
    <truncated>0</truncated>
    <difficult>0</difficult>
    <bndbox>
      <xmin>652.0</xmin>
      <ymin>161.0</ymin>
      <xmax>680.0</xmax>
      <ymax>269.0</ymax>
    </bndbox>
  </object>
</annotation>
